{"learner":{"attributes":{"best_iteration":"62","best_score":"0.6971127981240415"},"feature_names":["user_reorder_rate","user_avg_basket_size","user_order_frequency_per_week","user_cuisine_diversity","user_history_length","user_average_rating","business_rating","business_open","business_prep_time_minutes","cuisine_match","price_match","rating_gap_to_user_average","user_dominant_cuisine__American","user_dominant_cuisine__French","user_dominant_cuisine__Mediterranean","user_dominant_cuisine__Mexican","user_dominant_price__0-100k","user_dominant_price__100-250k","user_dominant_price__250-500k","user_dominant_price__500k+","business_cuisine__American","business_cuisine__French","business_cuisine__Mediterranean","business_cuisine__Mexican","business_price__0-100k","business_price__100-250k","business_price__250-500k","business_price__500k+","user_tag_presence__bike-parking","user_tag_presence__accessible","user_tag_presence__family-friendly","user_tag_presence__takeout","user_tag_presence__shopping","user_tag_presence__event planning & services","user_tag_presence__home services","user_tag_presence__beauty & spas","user_tag_presence__local services","user_tag_presence__arts & entertainment","user_tag_presence__health & medical","user_tag_presence__hotels & travel","user_tag_presence__active life","user_tag_presence__outdoor-seating","user_tag_presence__has-tv","user_tag_presence__nightlife","user_tag_presence__bars","user_tag_presence__breakfast & brunch","user_tag_presence__pets","user_tag_presence__delivery","user_tag_presence__venues & event spaces","user_tag_presence__home & garden","user_tag_presence__reservations","user_tag_presence__dog-friendly","user_tag_presence__tours","user_tag_presence__hair salons","user_tag_presence__art galleries","user_tag_presence__transportation","user_tag_presence__landmarks & historical buildings","user_tag_presence__public services & government","user_tag_presence__museums","user_tag_presence__local flavor","user_tag_presence__pet services","user_tag_presence__home decor","user_tag_presence__arts & crafts","user_tag_presence__massage","user_tag_presence__professional services","user_tag_presence__real estate","user_tag_presence__massage therapy","user_tag_presence__sandwiches","user_tag_presence__desserts","user_tag_presence__cafes","user_tag_presence__american (new)","user_tag_presence__american (traditional)","user_tag_presence__pet stores","user_tag_presence__jewelry","user_tag_presence__fitness & instruction","user_tag_presence__doctors","user_tag_presence__music venues","user_tag_presence__pet groomers","business_tag_presence__bike-parking","business_tag_presence__accessible","business_tag_presence__family-friendly","business_tag_presence__takeout","business_tag_presence__shopping","business_tag_presence__event planning & services","business_tag_presence__home services","business_tag_presence__beauty & spas","business_tag_presence__local services","business_tag_presence__arts & entertainment","business_tag_presence__health & medical","business_tag_presence__hotels & travel","business_tag_presence__active life","business_tag_presence__outdoor-seating","business_tag_presence__has-tv","business_tag_presence__nightlife","business_tag_presence__bars","business_tag_presence__breakfast & brunch","business_tag_presence__pets","business_tag_presence__delivery","business_tag_presence__venues & event spaces","business_tag_presence__home & garden","business_tag_presence__reservations","business_tag_presence__dog-friendly","business_tag_presence__tours","business_tag_presence__hair salons","business_tag_presence__art galleries","business_tag_presence__transportation","business_tag_presence__landmarks & historical buildings","business_tag_presence__public services & government","business_tag_presence__museums","business_tag_presence__local flavor","business_tag_presence__pet services","business_tag_presence__home decor","business_tag_presence__arts & crafts","business_tag_presence__massage","business_tag_presence__professional services","business_tag_presence__real estate","business_tag_presence__massage therapy","business_tag_presence__sandwiches","business_tag_presence__desserts","business_tag_presence__cafes","business_tag_presence__american (new)","business_tag_presence__american (traditional)","business_tag_presence__pet stores","business_tag_presence__jewelry","business_tag_presence__fitness & instruction","business_tag_presence__doctors","business_tag_presence__music venues","business_tag_presence__pet groomers"],"feature_types":[],"gradient_booster":{"model":{"cats":{"enc":[],"feature_segments":[],"sorted_idx":[]},"gbtree_model_param":{"num_parallel_tree":"1","num_trees":"83"},"iteration_indptr":[0,1,2,3,4,5,6,7,8,9,10,11,12,13,14,15,16,17,18,19,20,21,22,23,24,25,26,27,28,29,30,31,32,33,34,35,36,37,38,39,40,41,42,43,44,45,46,47,48,49,50,51,52,53,54,55,56,57,58,59,60,61,62,63,64,65,66,67,68,69,70,71,72,73,74,75,76,77,78,79,80,81,82,83],"tree_info":[0,0,0,0,0,0,0,0,0,0,0,0,0,0,0,0,0,0,0,0,0,0,0,0,0,0,0,0,0,0,0,0,0,0,0,0,0,0,0,0,0,0,0,0,0,0,0,0,0,0,0,0,0,0,0,0,0,0,0,0,0,0,0,0,0,0,0,0,0,0,0,0,0,0,0,0,0,0,0,0,0,0,0],"trees":[{"base_weights":[-5.999495E-3,-2.9723534E-1,3.7194657E-1,-1.920917E-2,1.3003865E-2,3.3197266E-3,2.9712215E-2],"categories":[],"categories_nodes":[],"categories_segments":[],"categories_sizes":[],"default_left":[0,0,0,0,0,0,0],"id":0,"left_children":[1,3,5,-1,-1,-1,-1],"loss_changes":[2.057254E1,6.1087685E0,5.135269E0,0E0,0E0,0E0,0E0],"parents":[2147483647,0,0,1,1,2,2],"right_children":[2,4,6,-1,-1,-1,-1],"split_conditions":[1E0,1E0,5E0,-1.920917E-2,1.3003865E-2,3.3197266E-3,2.9712215E-2],"split_indices":[78,91,6,0,0,0,0],"split_type":[0,0,0,0,0,0,0],"sum_hessian":[1.6685773E2,9.544539E1,7.141234E1,8.525153E1,1.0193854E1,3.5543682E1,3.5868652E1],"tree_param":{"num_deleted":"0","num_feature":"128","num_nodes":"7","size_leaf_vector":"1"}},{"base_weights":[8.552517E-3,-3.2178506E-1,2.3087464E-1,-2.6095754E-2,1.1344882E-2,1.6579595E-4,2.3826605E-2],"categories":[],"categories_nodes":[],"categories_segments":[],"categories_sizes":[],"default_left":[0,0,0,0,0,0,0],"id":1,"left_children":[1,3,5,-1,-1,-1,-1],"loss_changes":[2.0398455E1,1.3465254E1,9.252363E0,0E0,0E0,0E0,0E0],"parents":[2147483647,0,0,1,1,2,2],"right_children":[2,4,6,-1,-1,-1,-1],"split_conditions":[1E0,1E0,5E0,-2.6095754E-2,1.1344882E-2,1.6579595E-4,2.3826605E-2],"split_indices":[78,81,6,0,0,0,0],"split_type":[0,0,0,0,0,0,0],"sum_hessian":[2.576358E2,1.0184117E2,1.5579463E2,7.498025E1,2.6860924E1,8.613789E1,6.9656746E1],"tree_param":{"num_deleted":"0","num_feature":"128","num_nodes":"7","size_leaf_vector":"1"}},{"base_weights":[-1.3125881E-2,-2.1127121E-1,2.3294486E-1,-1.8081745E-2,1.3867249E-2,1.5238634E-2,-4.612099E-3],"categories":[],"categories_nodes":[],"categories_segments":[],"categories_sizes":[],"default_left":[0,0,0,0,0,0,0],"id":2,"left_children":[1,3,5,-1,-1,-1,-1],"loss_changes":[1.2932917E1,1.1772617E1,3.0506082E0,0E0,0E0,0E0,0E0],"parents":[2147483647,0,0,1,1,2,2],"right_children":[2,4,6,-1,-1,-1,-1],"split_conditions":[1E0,1E0,1E0,-1.8081745E-2,1.3867249E-2,1.5238634E-2,-4.612099E-3],"split_indices":[79,92,3,0,0,0,0],"split_type":[0,0,0,0,0,0,0],"sum_hessian":[2.4515465E2,1.3658528E2,1.0856935E2,1.0643151E2,3.0153774E1,8.944119E1,1.9128157E1],"tree_param":{"num_deleted":"0","num_feature":"128","num_nodes":"7","size_leaf_vector":"1"}},{"base_weights":[-2.7141476E-3,-2.8668287E-1,1.8166201E-1,-2.4395589E-2,7.846681E-3,-8.253138E-3,1.651969E-2],"categories":[],"categories_nodes":[],"categories_segments":[],"categories_sizes":[],"default_left":[0,0,0,0,0,0,0],"id":3,"left_children":[1,3,5,-1,-1,-1,-1],"loss_changes":[1.3738832E1,9.984102E0,8.754805E0,0E0,0E0,0E0,0E0],"parents":[2147483647,0,0,1,1,2,2],"right_children":[2,4,6,-1,-1,-1,-1],"split_conditions":[1E0,1E0,1E0,-2.4395589E-2,7.846681E-3,-8.253138E-3,1.651969E-2],"split_indices":[78,80,10,0,0,0,0],"split_type":[0,0,0,0,0,0,0],"sum_hessian":[2.4245953E2,9.326608E1,1.4919345E2,6.3474777E1,2.9791302E1,4.4456978E1,1.0473647E2],"tree_param":{"num_deleted":"0","num_feature":"128","num_nodes":"7","size_leaf_vector":"1"}},{"base_weights":[-3.2888053E-3,-1.2798987E-1,2.621122E-1,-2.7282884E-2,9.455758E-3,-9.884312E-3,3.0887475E-2],"categories":[],"categories_nodes":[],"categories_segments":[],"categories_sizes":[],"default_left":[0,0,0,0,0,0,0],"id":4,"left_children":[1,3,5,-1,-1,-1,-1],"loss_changes":[8.585493E0,2.4383417E1,1.4787839E1,0E0,0E0,0E0,0E0],"parents":[2147483647,0,0,1,1,2,2],"right_children":[2,4,6,-1,-1,-1,-1],"split_conditions":[1E0,1.7E-1,1E0,-2.7282884E-2,9.455758E-3,-9.884312E-3,3.0887475E-2],"split_indices":[81,11,47,0,0,0,0],"split_type":[0,0,0,0,0,0,0],"sum_hessian":[2.392769E2,1.6631146E2,7.296545E1,6.866431E1,9.764715E1,3.3759552E1,3.9205894E1],"tree_param":{"num_deleted":"0","num_feature":"128","num_nodes":"7","size_leaf_vector":"1"}},{"base_weights":[-3.168265E-3,-1.3414171E-1,2.7081683E-1,-1.7857341E-2,4.8077777E-3,-1.3944392E-2,1.7384326E-2],"categories":[],"categories_nodes":[],"categories_segments":[],"categories_sizes":[],"default_left":[0,0,0,0,0,0,0],"id":5,"left_children":[1,3,5,-1,-1,-1,-1],"loss_changes":[9.22224E0,9.265001E0,4.483508E0,0E0,0E0,0E0,0E0],"parents":[2147483647,0,0,1,1,2,2],"right_children":[2,4,6,-1,-1,-1,-1],"split_conditions":[1E0,1E0,1E0,-1.7857341E-2,4.8077777E-3,-1.3944392E-2,1.7384326E-2],"split_indices":[80,79,20,0,0,0,0],"split_type":[0,0,0,0,0,0,0],"sum_hessian":[2.3687247E2,1.6371542E2,7.315704E1,8.037619E1,8.3339226E1,5.7509155E0,6.740613E1],"tree_param":{"num_deleted":"0","num_feature":"128","num_nodes":"7","size_leaf_vector":"1"}},{"base_weights":[-6.216211E-3,-2.1485007E-1,1.3888285E-1,-1.9848695E-2,8.529476E-3,-9.28309E-3,1.3212467E-2],"categories":[],"categories_nodes":[],"categories_segments":[],"categories_sizes":[],"default_left":[0,0,0,0,0,0,0],"id":6,"left_children":[1,3,5,-1,-1,-1,-1],"loss_changes":[7.744362E0,8.035267E0,6.640251E0,0E0,0E0,0E0,0E0],"parents":[2147483647,0,0,1,1,2,2],"right_children":[2,4,6,-1,-1,-1,-1],"split_conditions":[1E0,1E0,1E0,-1.9848695E-2,8.529476E-3,-9.28309E-3,1.3212467E-2],"split_indices":[78,81,10,0,0,0,0],"split_type":[0,0,0,0,0,0,0],"sum_hessian":[2.3596426E2,9.481923E1,1.4114503E2,6.418973E1,3.06295E1,3.7989517E1,1.03155525E2],"tree_param":{"num_deleted":"0","num_feature":"128","num_nodes":"7","size_leaf_vector":"1"}},{"base_weights":[2.4892972E-3,-2.103819E-1,1.309688E-1,-2.0153252E-2,1.2694289E-2,-4.2029154E-3,1.05479425E-2],"categories":[],"categories_nodes":[],"categories_segments":[],"categories_sizes":[],"default_left":[0,0,0,0,0,0,0],"id":7,"left_children":[1,3,5,-1,-1,-1,-1],"loss_changes":[7.0218773E0,9.671995E0,2.9291737E0,0E0,0E0,0E0,0E0],"parents":[2147483647,0,0,1,1,2,2],"right_children":[2,4,6,-1,-1,-1,-1],"split_conditions":[1E0,1E0,1E0,-2.0153252E-2,1.2694289E-2,-4.2029154E-3,1.05479425E-2],"split_indices":[78,92,10,0,0,0,0],"split_type":[0,0,0,0,0,0,0],"sum_hessian":[2.3667079E2,8.668012E1,1.4999068E2,6.218853E1,2.449159E1,4.053012E1,1.0946055E2],"tree_param":{"num_deleted":"0","num_feature":"128","num_nodes":"7","size_leaf_vector":"1"}},{"base_weights":[1.13626355E-2,-1.0418246E-1,2.682431E-1,-2.2623058E-2,5.2211764E-3,-8.523972E-3,2.9324913E-2],"categories":[],"categories_nodes":[],"categories_segments":[],"categories_sizes":[],"default_left":[0,0,0,0,0,0,0],"id":8,"left_children":[1,3,5,-1,-1,-1,-1],"loss_changes":[7.631243E0,1.340815E1,1.2120144E1,0E0,0E0,0E0,0E0],"parents":[2147483647,0,0,1,1,2,2],"right_children":[2,4,6,-1,-1,-1,-1],"split_conditions":[1E0,5E0,1E0,-2.2623058E-2,5.2211764E-3,-8.523972E-3,2.9324913E-2],"split_indices":[81,6,47,0,0,0,0],"split_type":[0,0,0,0,0,0,0],"sum_hessian":[2.3769084E2,1.6804732E2,6.9643524E1,5.8570698E1,1.0947661E2,3.1232319E1,3.841121E1],"tree_param":{"num_deleted":"0","num_feature":"128","num_nodes":"7","size_leaf_vector":"1"}},{"base_weights":[-4.9119275E-3,-2.1108484E-1,1.2169168E-1,-1.8488701E-2,4.3758596E-3,-6.0596964E-3,1.0196178E-2],"categories":[],"categories_nodes":[],"categories_segments":[],"categories_sizes":[],"default_left":[0,0,0,0,0,0,0],"id":9,"left_children":[1,3,5,-1,-1,-1,-1],"loss_changes":[6.588791E0,4.870012E0,3.3756123E0,0E0,0E0,0E0,0E0],"parents":[2147483647,0,0,1,1,2,2],"right_children":[2,4,6,-1,-1,-1,-1],"split_conditions":[1E0,1E0,1E0,-1.8488701E-2,4.3758596E-3,-6.0596964E-3,1.0196178E-2],"split_indices":[78,80,10,0,0,0,0],"split_type":[0,0,0,0,0,0,0],"sum_hessian":[2.3258145E2,8.594608E1,1.4663538E2,5.4564693E1,3.1381392E1,3.589005E1,1.1074532E2],"tree_param":{"num_deleted":"0","num_feature":"128","num_nodes":"7","size_leaf_vector":"1"}},{"base_weights":[-2.5844181E-2,-1.435448E-1,2.1533743E-1,-1.1378217E-2,1.1126892E-2,-1.7634092E-3,2.1835167E-2],"categories":[],"categories_nodes":[],"categories_segments":[],"categories_sizes":[],"default_left":[0,0,0,0,0,0,0],"id":10,"left_children":[1,3,5,-1,-1,-1,-1],"loss_changes":[7.0232944E0,5.579996E0,4.67918E0,0E0,0E0,0E0,0E0],"parents":[2147483647,0,0,1,1,2,2],"right_children":[2,4,6,-1,-1,-1,-1],"split_conditions":[1E0,1E0,1E0,-1.1378217E-2,1.1126892E-2,-1.7634092E-3,2.1835167E-2],"split_indices":[80,81,47,0,0,0,0],"split_type":[0,0,0,0,0,0,0],"sum_hessian":[2.265215E2,1.5495108E2,7.157043E1,1.2910422E2,2.584687E1,3.7511223E1,3.40592E1],"tree_param":{"num_deleted":"0","num_feature":"128","num_nodes":"7","size_leaf_vector":"1"}},{"base_weights":[4.3718196E-3,-2.0733683E-1,1.2970962E-1,-1.6816597E-2,7.0696445E-3,-3.6500703E-4,1.5087815E-2],"categories":[],"categories_nodes":[],"categories_segments":[],"categories_sizes":[],"default_left":[0,0,0,0,0,0,0],"id":11,"left_children":[1,3,5,-1,-1,-1,-1],"loss_changes":[6.573418E0,4.6231756E0,3.6848688E0,0E0,0E0,0E0,0E0],"parents":[2147483647,0,0,1,1,2,2],"right_children":[2,4,6,-1,-1,-1,-1],"split_conditions":[1E0,1E0,1E0,-1.6816597E-2,7.0696445E-3,-3.6500703E-4,1.5087815E-2],"split_indices":[78,92,9,0,0,0,0],"split_type":[0,0,0,0,0,0,0],"sum_hessian":[2.2759032E2,8.220137E1,1.4538895E2,6.02649E1,2.193647E1,8.626628E1,5.912266E1],"tree_param":{"num_deleted":"0","num_feature":"128","num_nodes":"7","size_leaf_vector":"1"}},{"base_weights":[1.5156729E-2,-1.7761225E-1,1.2588666E-1,-1.6519323E-2,5.5421996E-3,-2.3755624E-3,1.2203834E-2],"categories":[],"categories_nodes":[],"categories_segments":[],"categories_sizes":[],"default_left":[0,0,0,0,0,0,0],"id":12,"left_children":[1,3,5,-1,-1,-1,-1],"loss_changes":[5.2825937E0,4.359668E0,3.3209844E0,0E0,0E0,0E0,0E0],"parents":[2147483647,0,0,1,1,2,2],"right_children":[2,4,6,-1,-1,-1,-1],"split_conditions":[1E0,1E0,1.7E-1,-1.6519323E-2,5.5421996E-3,-2.3755624E-3,1.2203834E-2],"split_indices":[78,81,11,0,0,0,0],"split_type":[0,0,0,0,0,0,0],"sum_hessian":[2.2700789E2,8.061889E1,1.4638899E2,5.1754635E1,2.8864256E1,6.1760113E1,8.4628876E1],"tree_param":{"num_deleted":"0","num_feature":"128","num_nodes":"7","size_leaf_vector":"1"}},{"base_weights":[-6.808775E-3,-2.1901138E-1,1.0091703E-1,-1.7545952E-2,3.143184E-3,5.4542616E-5,1.1472528E-2],"categories":[],"categories_nodes":[],"categories_segments":[],"categories_sizes":[],"default_left":[0,0,0,0,0,0,0],"id":13,"left_children":[1,3,5,-1,-1,-1,-1],"loss_changes":[5.6650233E0,3.3194296E0,2.1121137E0,0E0,0E0,0E0,0E0],"parents":[2147483647,0,0,1,1,2,2],"right_children":[2,4,6,-1,-1,-1,-1],"split_conditions":[1E0,1E0,1E0,-1.7545952E-2,3.143184E-3,5.4542616E-5,1.1472528E-2],"split_indices":[78,81,9,0,0,0,0],"split_type":[0,0,0,0,0,0,0],"sum_hessian":[2.2814854E2,7.334337E1,1.5480518E2,4.8294014E1,2.5049356E1,9.280927E1,6.199589E1],"tree_param":{"num_deleted":"0","num_feature":"128","num_nodes":"7","size_leaf_vector":"1"}},{"base_weights":[1.9314006E-2,-1.957112E-1,1.2850082E-1,-1.799476E-2,5.208414E-3,-1.9130682E-3,9.111762E-3],"categories":[],"categories_nodes":[],"categories_segments":[],"categories_sizes":[],"default_left":[0,0,0,0,0,0,0],"id":14,"left_children":[1,3,5,-1,-1,-1,-1],"loss_changes":[5.774203E0,4.470462E0,1.5218053E0,0E0,0E0,0E0,0E0],"parents":[2147483647,0,0,1,1,2,2],"right_children":[2,4,6,-1,-1,-1,-1],"split_conditions":[1E0,1E0,1E0,-1.799476E-2,5.208414E-3,-1.9130682E-3,9.111762E-3],"split_indices":[78,81,10,0,0,0,0],"split_type":[0,0,0,0,0,0,0],"sum_hessian":[2.2523009E2,7.318332E1,1.5204677E2,4.599806E1,2.7185263E1,3.775511E1,1.1429165E2],"tree_param":{"num_deleted":"0","num_feature":"128","num_nodes":"7","size_leaf_vector":"1"}},{"base_weights":[6.4369715E-3,-8.088887E-2,2.1306041E-1,-2.1711012E-2,4.6568536E-3,-7.0198923E-3,2.5562022E-2],"categories":[],"categories_nodes":[],"categories_segments":[],"categories_sizes":[],"default_left":[0,0,0,0,0,0,0],"id":15,"left_children":[1,3,5,-1,-1,-1,-1],"loss_changes":[4.473926E0,1.1154188E1,8.472164E0,0E0,0E0,0E0,0E0],"parents":[2147483647,0,0,1,1,2,2],"right_children":[2,4,6,-1,-1,-1,-1],"split_conditions":[1E0,1.7E-1,1E0,-2.1711012E-2,4.6568536E-3,-7.0198923E-3,2.5562022E-2],"split_indices":[81,11,47,0,0,0,0],"split_type":[0,0,0,0,0,0,0],"sum_hessian":[2.283999E2,1.6482475E2,6.357514E1,4.9457626E1,1.1536713E2,3.151236E1,3.2062782E1],"tree_param":{"num_deleted":"0","num_feature":"128","num_nodes":"7","size_leaf_vector":"1"}},{"base_weights":[-1.4379933E-2,-2.296728E-1,9.2735454E-2,-1.8175127E-2,1.8207977E-3,-2.4020972E-3,1.4087088E-2],"categories":[],"categories_nodes":[],"categories_segments":[],"categories_sizes":[],"default_left":[0,0,0,0,0,0,0],"id":16,"left_children":[1,3,5,-1,-1,-1,-1],"loss_changes":[5.562763E0,2.9793997E0,4.446697E0,0E0,0E0,0E0,0E0],"parents":[2147483647,0,0,1,1,2,2],"right_children":[2,4,6,-1,-1,-1,-1],"split_conditions":[1E0,1E0,1E0,-1.8175127E-2,1.8207977E-3,-2.4020972E-3,1.4087088E-2],"split_indices":[78,80,9,0,0,0,0],"split_type":[0,0,0,0,0,0,0],"sum_hessian":[2.2198184E2,6.994888E1,1.5203296E2,4.410517E1,2.5843714E1,9.140789E1,6.0625076E1],"tree_param":{"num_deleted":"0","num_feature":"128","num_nodes":"7","size_leaf_vector":"1"}},{"base_weights":[-1.5744213E-2,-1.943224E-1,7.337389E-2,-1.5916368E-2,4.820151E-3,-2.489199E-3,1.171923E-2],"categories":[],"categories_nodes":[],"categories_segments":[],"categories_sizes":[],"default_left":[0,0,0,0,0,0,0],"id":17,"left_children":[1,3,5,-1,-1,-1,-1],"loss_changes":[3.8522327E0,3.2032826E0,3.3441145E0,0E0,0E0,0E0,0E0],"parents":[2147483647,0,0,1,1,2,2],"right_children":[2,4,6,-1,-1,-1,-1],"split_conditions":[1E0,1E0,1E0,-1.5916368E-2,4.820151E-3,-2.489199E-3,1.171923E-2],"split_indices":[78,92,9,0,0,0,0],"split_type":[0,0,0,0,0,0,0],"sum_hessian":[2.2309805E2,7.034103E1,1.5275703E2,4.8643425E1,2.1697601E1,9.046667E1,6.2290367E1],"tree_param":{"num_deleted":"0","num_feature":"128","num_nodes":"7","size_leaf_vector":"1"}},{"base_weights":[-1.2739238E-2,-1.11210406E-1,2.0024619E-1,-8.753794E-3,1.3781969E-2,-4.3878076E-3,1.6305966E-2],"categories":[],"categories_nodes":[],"categories_segments":[],"categories_sizes":[],"default_left":[0,0,0,0,0,0,0],"id":18,"left_children":[1,3,5,-1,-1,-1,-1],"loss_changes":[5.1706843E0,4.6273637E0,3.1196563E0,0E0,0E0,0E0,0E0],"parents":[2147483647,0,0,1,1,2,2],"right_children":[2,4,6,-1,-1,-1,-1],"split_conditions":[1E0,1E0,1E0,-8.753794E-3,1.3781969E-2,-4.3878076E-3,1.6305966E-2],"split_indices":[80,91,25,0,0,0,0],"split_type":[0,0,0,0,0,0,0],"sum_hessian":[2.2592276E2,1.5776198E2,6.816079E1,1.4010602E2,1.7655947E1,2.1650915E1,4.6509876E1],"tree_param":{"num_deleted":"0","num_feature":"128","num_nodes":"7","size_leaf_vector":"1"}},{"base_weights":[-5.0339717E-3,-6.6651985E-2,2.4052452E-1,-1.673103E-2,4.760684E-3,2.3097754E-2,-5.29282E-3],"categories":[],"categories_nodes":[],"categories_segments":[],"categories_sizes":[],"default_left":[0,0,0,0,0,0,0],"id":19,"left_children":[1,3,5,-1,-1,-1,-1],"loss_changes":[3.7310734E0,8.841067E0,4.28629E0,0E0,0E0,0E0,0E0],"parents":[2147483647,0,0,1,1,2,2],"right_children":[2,4,6,-1,-1,-1,-1],"split_conditions":[1E0,5E0,1E0,-1.673103E-2,4.760684E-3,2.3097754E-2,-5.29282E-3],"split_indices":[91,6,12,0,0,0,0],"split_type":[0,0,0,0,0,0,0],"sum_hessian":[2.2599232E2,1.8648366E2,3.9508667E1,6.620633E1,1.2027733E2,2.2065962E1,1.7442705E1],"tree_param":{"num_deleted":"0","num_feature":"128","num_nodes":"7","size_leaf_vector":"1"}},{"base_weights":[-1.916031E-2,-9.044727E-2,1.5673178E-1,-1.53757995E-2,2.362642E-3,-4.090188E-3,1.8253973E-2],"categories":[],"categories_nodes":[],"categories_segments":[],"categories_sizes":[],"default_left":[0,0,0,0,0,0,0],"id":20,"left_children":[1,3,5,-1,-1,-1,-1],"loss_changes":[3.133156E0,5.409228E0,3.8999648E0,0E0,0E0,0E0,0E0],"parents":[2147483647,0,0,1,1,2,2],"right_children":[2,4,6,-1,-1,-1,-1],"split_conditions":[1E0,1E0,1E0,-1.53757995E-2,2.362642E-3,-4.090188E-3,1.8253973E-2],"split_indices":[80,79,47,0,0,0,0],"split_type":[0,0,0,0,0,0,0],"sum_hessian":[2.2857095E2,1.661074E2,6.2463543E1,5.9686333E1,1.06421074E2,3.19537E1,3.0509844E1],"tree_param":{"num_deleted":"0","num_feature":"128","num_nodes":"7","size_leaf_vector":"1"}},{"base_weights":[-7.6743937E-3,-5.2204143E-2,1.9851482E-1,-1.279634E-2,3.9335024E-3,2.0309478E-2,-8.374865E-3],"categories":[],"categories_nodes":[],"categories_segments":[],"categories_sizes":[],"default_left":[0,0,0,0,0,0,0],"id":21,"left_children":[1,3,5,-1,-1,-1,-1],"loss_changes":[2.2089615E0,5.440218E0,3.9342334E0,0E0,0E0,0E0,0E0],"parents":[2147483647,0,0,1,1,2,2],"right_children":[2,4,6,-1,-1,-1,-1],"split_conditions":[1E0,5E0,9E-1,-1.279634E-2,3.9335024E-3,2.0309478E-2,-8.374865E-3],"split_indices":[91,6,0,0,0,0,0],"split_type":[0,0,0,0,0,0,0],"sum_hessian":[2.1929982E2,1.8649211E2,3.2807713E1,6.920711E1,1.17285E2,2.0230976E1,1.2576735E1],"tree_param":{"num_deleted":"0","num_feature":"128","num_nodes":"7","size_leaf_vector":"1"}},{"base_weights":[-1.3687279E-2,-1.820124E-1,7.314917E-2,-1.4797418E-2,3.351926E-3,-3.5255097E-3,8.12897E-3],"categories":[],"categories_nodes":[],"categories_segments":[],"categories_sizes":[],"default_left":[0,0,0,0,0,0,0],"id":22,"left_children":[1,3,5,-1,-1,-1,-1],"loss_changes":[3.505407E0,2.507703E0,2.161622E0,0E0,0E0,0E0,0E0],"parents":[2147483647,0,0,1,1,2,2],"right_children":[2,4,6,-1,-1,-1,-1],"split_conditions":[1E0,1E0,5E0,-1.4797418E-2,3.351926E-3,-3.5255097E-3,8.12897E-3],"split_indices":[78,81,6,0,0,0,0],"split_type":[0,0,0,0,0,0,0],"sum_hessian":[2.2071239E2,7.13827E1,1.493297E2,4.7684788E1,2.369791E1,5.810551E1,9.122418E1],"tree_param":{"num_deleted":"0","num_feature":"128","num_nodes":"7","size_leaf_vector":"1"}},{"base_weights":[-8.041879E-3,-1.725052E-1,7.380523E-2,-1.5856707E-2,4.5734295E-3,-1.126706E-3,9.527184E-3],"categories":[],"categories_nodes":[],"categories_segments":[],"categories_sizes":[],"default_left":[0,0,0,0,0,0,0],"id":23,"left_children":[1,3,5,-1,-1,-1,-1],"loss_changes":[3.307573E0,3.4017487E0,1.8958657E0,0E0,0E0,0E0,0E0],"parents":[2147483647,0,0,1,1,2,2],"right_children":[2,4,6,-1,-1,-1,-1],"split_conditions":[1E0,1E0,1E0,-1.5856707E-2,4.5734295E-3,-1.126706E-3,9.527184E-3],"split_indices":[78,81,9,0,0,0,0],"split_type":[0,0,0,0,0,0,0],"sum_hessian":[2.2625967E2,7.1503746E1,1.5475594E2,4.4893265E1,2.6610481E1,8.920691E1,6.554903E1],"tree_param":{"num_deleted":"0","num_feature":"128","num_nodes":"7","size_leaf_vector":"1"}},{"base_weights":[-2.275769E-3,-1.7331095E-1,8.4822364E-2,-1.4251967E-2,5.116297E-3,-1.4954194E-3,1.1538931E-2],"categories":[],"categories_nodes":[],"categories_segments":[],"categories_sizes":[],"default_left":[0,0,0,0,0,0,0],"id":24,"left_children":[1,3,5,-1,-1,-1,-1],"loss_changes":[3.6092823E0,2.8079548E0,2.7602153E0,0E0,0E0,0E0,0E0],"parents":[2147483647,0,0,1,1,2,2],"right_children":[2,4,6,-1,-1,-1,-1],"split_conditions":[1E0,1E0,1E0,-1.4251967E-2,5.116297E-3,-1.4954194E-3,1.1538931E-2],"split_indices":[78,92,9,0,0,0,0],"split_type":[0,0,0,0,0,0,0],"sum_hessian":[2.2241672E2,7.170695E1,1.5070978E2,5.078167E1,2.092528E1,8.8832634E1,6.187714E1],"tree_param":{"num_deleted":"0","num_feature":"128","num_nodes":"7","size_leaf_vector":"1"}},{"base_weights":[8.464555E-3,-1.468466E-1,8.398301E-2,-1.29689695E-2,5.4408535E-3,-1.382287E-3,1.1393232E-2],"categories":[],"categories_nodes":[],"categories_segments":[],"categories_sizes":[],"default_left":[0,0,0,0,0,0,0],"id":25,"left_children":[1,3,5,-1,-1,-1,-1],"loss_changes":[2.90306E0,2.617707E0,2.7263513E0,0E0,0E0,0E0,0E0],"parents":[2147483647,0,0,1,1,2,2],"right_children":[2,4,6,-1,-1,-1,-1],"split_conditions":[1E0,1E0,1E0,-1.29689695E-2,5.4408535E-3,-1.382287E-3,1.1393232E-2],"split_indices":[78,92,9,0,0,0,0],"split_type":[0,0,0,0,0,0,0],"sum_hessian":[2.269995E2,7.117531E1,1.5582419E2,4.932091E1,2.18544E1,9.2296036E1,6.3528145E1],"tree_param":{"num_deleted":"0","num_feature":"128","num_nodes":"7","size_leaf_vector":"1"}},{"base_weights":[3.401909E-2,-1.5347208E-1,1.2196719E-1,-1.5202283E-2,4.638513E-3,-1.6539429E-3,8.758196E-3],"categories":[],"categories_nodes":[],"categories_segments":[],"categories_sizes":[],"default_left":[0,0,0,0,0,0,0],"id":26,"left_children":[1,3,5,-1,-1,-1,-1],"loss_changes":[4.0159464E0,3.1951733E0,1.4075205E0,0E0,0E0,0E0,0E0],"parents":[2147483647,0,0,1,1,2,2],"right_children":[2,4,6,-1,-1,-1,-1],"split_conditions":[1E0,1E0,1E0,-1.5202283E-2,4.638513E-3,-1.6539429E-3,8.758196E-3],"split_indices":[78,81,10,0,0,0,0],"split_type":[0,0,0,0,0,0,0],"sum_hessian":[2.2219398E2,6.8567924E1,1.5362605E2,4.109284E1,2.7475086E1,4.021067E1,1.1341538E2],"tree_param":{"num_deleted":"0","num_feature":"128","num_nodes":"7","size_leaf_vector":"1"}},{"base_weights":[-3.5983603E-3,-7.779146E-2,1.6488542E-1,-7.2752284E-3,1.0562307E-2,-5.3866743E-3,1.4281645E-2],"categories":[],"categories_nodes":[],"categories_segments":[],"categories_sizes":[],"default_left":[0,0,0,0,0,0,0],"id":27,"left_children":[1,3,5,-1,-1,-1,-1],"loss_changes":[3.0420182E0,3.6076393E0,2.7590928E0,0E0,0E0,0E0,0E0],"parents":[2147483647,0,0,1,1,2,2],"right_children":[2,4,6,-1,-1,-1,-1],"split_conditions":[1E0,1E0,1E0,-7.2752284E-3,1.0562307E-2,-5.3866743E-3,1.4281645E-2],"split_indices":[80,81,25,0,0,0,0],"split_type":[0,0,0,0,0,0,0],"sum_hessian":[2.2309389E2,1.5862502E2,6.446887E1,1.3254053E2,2.6084494E1,2.012016E1,4.434871E1],"tree_param":{"num_deleted":"0","num_feature":"128","num_nodes":"7","size_leaf_vector":"1"}},{"base_weights":[-5.226422E-3,-1.9163322E-1,8.601693E-2,-1.3885575E-2,5.074452E-3,-1.219325E-3,1.0476059E-2],"categories":[],"categories_nodes":[],"categories_segments":[],"categories_sizes":[],"default_left":[0,0,0,0,0,0,0],"id":28,"left_children":[1,3,5,-1,-1,-1,-1],"loss_changes":[3.95319E0,2.206871E0,2.184198E0,0E0,0E0,0E0,0E0],"parents":[2147483647,0,0,1,1,2,2],"right_children":[2,4,6,-1,-1,-1,-1],"split_conditions":[1E0,1E0,1E0,-1.3885575E-2,5.074452E-3,-1.219325E-3,1.0476059E-2],"split_indices":[78,95,9,0,0,0,0],"split_type":[0,0,0,0,0,0,0],"sum_hessian":[2.1273448E2,6.629461E1,1.4643987E2,5.1652176E1,1.4642431E1,8.155835E1,6.488152E1],"tree_param":{"num_deleted":"0","num_feature":"128","num_nodes":"7","size_leaf_vector":"1"}},{"base_weights":[-2.0594126E-2,-1.8192469E-1,5.4607973E-2,-1.2124333E-2,9.073186E-3,-6.8991594E-3,6.181129E-3],"categories":[],"categories_nodes":[],"categories_segments":[],"categories_sizes":[],"default_left":[0,0,0,0,0,0,0],"id":29,"left_children":[1,3,5,-1,-1,-1,-1],"loss_changes":[2.8204358E0,2.0601354E0,2.306098E0,0E0,0E0,0E0,0E0],"parents":[2147483647,0,0,1,1,2,2],"right_children":[2,4,6,-1,-1,-1,-1],"split_conditions":[1E0,4.3E-1,1E0,-1.2124333E-2,9.073186E-3,-6.8991594E-3,6.181129E-3],"split_indices":[78,11,10,0,0,0,0],"split_type":[0,0,0,0,0,0,0],"sum_hessian":[2.1428302E2,6.361619E1,1.5066682E2,5.738031E1,6.235883E0,3.711128E1,1.1355555E2],"tree_param":{"num_deleted":"0","num_feature":"128","num_nodes":"7","size_leaf_vector":"1"}},{"base_weights":[-9.25808E-3,-6.807145E-2,1.5236983E-1,-1.6599046E-2,3.2274649E-3,-6.0029915E-3,2.6973212E-2],"categories":[],"categories_nodes":[],"categories_segments":[],"categories_sizes":[],"default_left":[0,0,0,0,0,0,0],"id":30,"left_children":[1,3,5,-1,-1,-1,-1],"loss_changes":[2.3271627E0,6.4585905E0,7.554265E0,0E0,0E0,0E0,0E0],"parents":[2147483647,0,0,1,1,2,2],"right_children":[2,4,6,-1,-1,-1,-1],"split_conditions":[1E0,5E0,1E0,-1.6599046E-2,3.2274649E-3,-6.0029915E-3,2.6973212E-2],"split_indices":[81,6,15,0,0,0,0],"split_type":[0,0,0,0,0,0,0],"sum_hessian":[2.2390176E2,1.684092E2,5.5492573E1,5.1297356E1,1.1711184E2,3.6619152E1,1.887342E1],"tree_param":{"num_deleted":"0","num_feature":"128","num_nodes":"7","size_leaf_vector":"1"}},{"base_weights":[9.133796E-3,-5.7957064E-2,1.8863599E-1,-1.4727331E-2,2.7350502E-3,-5.645906E-3,2.843473E-2],"categories":[],"categories_nodes":[],"categories_segments":[],"categories_sizes":[],"default_left":[0,0,0,0,0,0,0],"id":31,"left_children":[1,3,5,-1,-1,-1,-1],"loss_changes":[2.9215481E0,4.8956885E0,8.192919E0,0E0,0E0,0E0,0E0],"parents":[2147483647,0,0,1,1,2,2],"right_children":[2,4,6,-1,-1,-1,-1],"split_conditions":[1E0,5E0,1E0,-1.4727331E-2,2.7350502E-3,-5.645906E-3,2.843473E-2],"split_indices":[81,6,15,0,0,0,0],"split_type":[0,0,0,0,0,0,0],"sum_hessian":[2.2351578E2,1.6763255E2,5.5883224E1,4.886583E1,1.1876673E2,3.5079018E1,2.0804207E1],"tree_param":{"num_deleted":"0","num_feature":"128","num_nodes":"7","size_leaf_vector":"1"}},{"base_weights":[6.2140576E-3,-1.7076431E-1,8.3630145E-2,-2.401742E-2,-1.5588705E-3,1.000658E-3,1.1963471E-2],"categories":[],"categories_nodes":[],"categories_segments":[],"categories_sizes":[],"default_left":[0,0,0,0,0,0,0],"id":32,"left_children":[1,3,5,-1,-1,-1,-1],"loss_changes":[3.2749445E0,2.9986258E0,1.5932633E0,0E0,0E0,0E0,0E0],"parents":[2147483647,0,0,1,1,2,2],"right_children":[2,4,6,-1,-1,-1,-1],"split_conditions":[1E0,1E0,1E0,-2.401742E-2,-1.5588705E-3,1.000658E-3,1.1963471E-2],"split_indices":[10,42,80,0,0,0,0],"split_type":[0,0,0,0,0,0,0],"sum_hessian":[2.1860666E2,6.2855892E1,1.5575078E2,1.1946997E1,5.0908894E1,1.1857113E2,3.7179646E1],"tree_param":{"num_deleted":"0","num_feature":"128","num_nodes":"7","size_leaf_vector":"1"}},{"base_weights":[-6.4851977E-3,-1.8574362E-1,4.560663E-2,-1.3678326E-2,1.0432856E-2,-1.8880834E-4,1.0309131E-2],"categories":[],"categories_nodes":[],"categories_segments":[],"categories_sizes":[],"default_left":[0,0,0,0,0,0,0],"id":33,"left_children":[1,3,5,-1,-1,-1,-1],"loss_changes":[2.248198E0,2.4460647E0,1.494995E0,0E0,0E0,0E0,0E0],"parents":[2147483647,0,0,1,1,2,2],"right_children":[2,4,6,-1,-1,-1,-1],"split_conditions":[-1.2E-1,1E0,1E0,-1.3678326E-2,1.0432856E-2,-1.8880834E-4,1.0309131E-2],"split_indices":[11,89,81,0,0,0,0],"split_type":[0,0,0,0,0,0,0],"sum_hessian":[2.2168881E2,4.4139385E1,1.7754942E2,3.860646E1,5.5329247E0,1.432575E2,3.4291916E1],"tree_param":{"num_deleted":"0","num_feature":"128","num_nodes":"7","size_leaf_vector":"1"}},{"base_weights":[-1.9545713E-2,-1.5160231E-1,7.751152E-2,-1.5313013E-2,8.951548E-3,3.8535064E-4,1.7294804E-2],"categories":[],"categories_nodes":[],"categories_segments":[],"categories_sizes":[],"default_left":[0,0,0,0,0,0,0],"id":34,"left_children":[1,3,5,-1,-1,-1,-1],"loss_changes":[3.0587478E0,5.6922264E0,2.5752528E0,0E0,0E0,0E0,0E0],"parents":[2147483647,0,0,1,1,2,2],"right_children":[2,4,6,-1,-1,-1,-1],"split_conditions":[5E0,1E0,1E0,-1.5313013E-2,8.951548E-3,3.8535064E-4,1.7294804E-2],"split_indices":[6,91,103,0,0,0,0],"split_type":[0,0,0,0,0,0,0],"sum_hessian":[2.1947865E2,9.059488E1,1.2888377E2,6.2225338E1,2.8369541E1,1.10445114E2,1.843866E1],"tree_param":{"num_deleted":"0","num_feature":"128","num_nodes":"7","size_leaf_vector":"1"}},{"base_weights":[1.2632246E-2,-1.3299783E-1,8.673021E-2,-1.3447675E-2,5.267305E-3,-3.769464E-3,7.483601E-3],"categories":[],"categories_nodes":[],"categories_segments":[],"categories_sizes":[],"default_left":[0,0,0,0,0,0,0],"id":35,"left_children":[1,3,5,-1,-1,-1,-1],"loss_changes":[2.640241E0,2.968101E0,1.7570336E0,0E0,0E0,0E0,0E0],"parents":[2147483647,0,0,1,1,2,2],"right_children":[2,4,6,-1,-1,-1,-1],"split_conditions":[1E0,1E0,1E0,-1.3447675E-2,5.267305E-3,-3.769464E-3,7.483601E-3],"split_indices":[78,80,10,0,0,0,0],"split_type":[0,0,0,0,0,0,0],"sum_hessian":[2.239836E2,7.285247E1,1.5113112E2,4.5572712E1,2.727976E1,4.171304E1,1.0941808E2],"tree_param":{"num_deleted":"0","num_feature":"128","num_nodes":"7","size_leaf_vector":"1"}},{"base_weights":[4.213558E-3,-1.03752606E-1,9.250645E-2,-1.6032634E-2,6.4657517E-3,1.05193565E-2,-1.3637206E-3],"categories":[],"categories_nodes":[],"categories_segments":[],"categories_sizes":[],"default_left":[0,0,0,0,0,0,0],"id":36,"left_children":[1,3,5,-1,-1,-1,-1],"loss_changes":[2.2794297E0,5.8620934E0,1.9111998E0,0E0,0E0,0E0,0E0],"parents":[2147483647,0,0,1,1,2,2],"right_children":[2,4,6,-1,-1,-1,-1],"split_conditions":[5E0,1E0,1E0,-1.6032634E-2,6.4657517E-3,1.05193565E-2,-1.3637206E-3],"split_indices":[6,81,47,0,0,0,0],"split_type":[0,0,0,0,0,0,0],"sum_hessian":[2.1904994E2,9.775832E1,1.2129162E2,4.868894E1,4.906938E1,5.7318287E1,6.3973335E1],"tree_param":{"num_deleted":"0","num_feature":"128","num_nodes":"7","size_leaf_vector":"1"}},{"base_weights":[-3.1064528E-3,-1.663175E-1,6.972626E-2,-1.5722677E-2,2.7811755E-3,1.170668E-2,-3.225318E-4],"categories":[],"categories_nodes":[],"categories_segments":[],"categories_sizes":[],"default_left":[0,0,0,0,0,0,0],"id":37,"left_children":[1,3,5,-1,-1,-1,-1],"loss_changes":[2.8474667E0,2.6031096E0,2.093227E0,0E0,0E0,0E0,0E0],"parents":[2147483647,0,0,1,1,2,2],"right_children":[2,4,6,-1,-1,-1,-1],"split_conditions":[1E0,1E0,5E0,-1.5722677E-2,2.7811755E-3,1.170668E-2,-3.225318E-4],"split_indices":[10,50,4,0,0,0,0],"split_type":[0,0,0,0,0,0,0],"sum_hessian":[2.1978685E2,6.385606E1,1.5593079E2,3.5795662E1,2.80604E1,4.2807278E1,1.13123505E2],"tree_param":{"num_deleted":"0","num_feature":"128","num_nodes":"7","size_leaf_vector":"1"}},{"base_weights":[1.9378286E-2,-8.527951E-2,1.10248305E-1,-8.664773E-3,9.514696E-3,6.524671E-4,1.0812845E-2],"categories":[],"categories_nodes":[],"categories_segments":[],"categories_sizes":[],"default_left":[0,0,0,0,0,0,0],"id":38,"left_children":[1,3,5,-1,-1,-1,-1],"loss_changes":[2.2748647E0,3.0514297E0,1.2814521E0,0E0,0E0,0E0,0E0],"parents":[2147483647,0,0,1,1,2,2],"right_children":[2,4,6,-1,-1,-1,-1],"split_conditions":[1E0,1E0,1E0,-8.664773E-3,9.514696E-3,6.524671E-4,1.0812845E-2],"split_indices":[79,92,9,0,0,0,0],"split_type":[0,0,0,0,0,0,0],"sum_hessian":[2.1931512E2,1.022109E2,1.1710422E2,8.02812E1,2.1929708E1,6.694944E1,5.0154778E1],"tree_param":{"num_deleted":"0","num_feature":"128","num_nodes":"7","size_leaf_vector":"1"}},{"base_weights":[2.6275758E-2,-1.5108983E-1,1.16829865E-1,-1.1173903E-2,1.1637009E-2,-2.522559E-3,8.734821E-3],"categories":[],"categories_nodes":[],"categories_segments":[],"categories_sizes":[],"default_left":[0,0,0,0,0,0,0],"id":39,"left_children":[1,3,5,-1,-1,-1,-1],"loss_changes":[3.7119424E0,2.7084436E0,1.553323E0,0E0,0E0,0E0,0E0],"parents":[2147483647,0,0,1,1,2,2],"right_children":[2,4,6,-1,-1,-1,-1],"split_conditions":[1E0,4.3E-1,4.58E0,-1.1173903E-2,1.1637009E-2,-2.522559E-3,8.734821E-3],"split_indices":[78,11,5,0,0,0,0],"split_type":[0,0,0,0,0,0,0],"sum_hessian":[2.1012228E2,6.8759705E1,1.4136258E2,6.1364395E1,7.395306E0,3.666182E1,1.0470076E2],"tree_param":{"num_deleted":"0","num_feature":"128","num_nodes":"7","size_leaf_vector":"1"}},{"base_weights":[-2.1381453E-3,-5.6091104E-2,1.5091433E-1,3.3854644E-3,-1.2549207E-2,-1.3812925E-2,1.9813936E-2],"categories":[],"categories_nodes":[],"categories_segments":[],"categories_sizes":[],"default_left":[0,0,0,0,0,0,0],"id":40,"left_children":[1,3,5,-1,-1,-1,-1],"loss_changes":[1.9595824E0,4.3963256E0,7.5814314E0,0E0,0E0,0E0,0E0],"parents":[2147483647,0,0,1,1,2,2],"right_children":[2,4,6,-1,-1,-1,-1],"split_conditions":[1E0,1E0,1E0,3.3854644E-3,-1.2549207E-2,-1.3812925E-2,1.9813936E-2],"split_indices":[81,15,42,0,0,0,0],"split_type":[0,0,0,0,0,0,0],"sum_hessian":[2.1705452E2,1.6516641E2,5.1888103E1,1.0499627E2,6.0170143E1,1.8471172E1,3.341693E1],"tree_param":{"num_deleted":"0","num_feature":"128","num_nodes":"7","size_leaf_vector":"1"}},{"base_weights":[-3.5370823E-3,-1.1008407E-1,7.796425E-2,-1.5812041E-2,6.085628E-3,1.2143032E-4,1.5294175E-2],"categories":[],"categories_nodes":[],"categories_segments":[],"categories_sizes":[],"default_left":[0,0,0,0,0,0,0],"id":41,"left_children":[1,3,5,-1,-1,-1,-1],"loss_changes":[2.0332394E0,5.2276664E0,2.280899E0,0E0,0E0,0E0,0E0],"parents":[2147483647,0,0,1,1,2,2],"right_children":[2,4,6,-1,-1,-1,-1],"split_conditions":[5E0,1E0,1E0,-1.5812041E-2,6.085628E-3,1.2143032E-4,1.5294175E-2],"split_indices":[6,81,80,0,0,0,0],"split_type":[0,0,0,0,0,0,0],"sum_hessian":[2.1426022E2,9.134177E1,1.2291845E2,4.6416523E1,4.4925243E1,9.9912575E1,2.3005877E1],"tree_param":{"num_deleted":"0","num_feature":"128","num_nodes":"7","size_leaf_vector":"1"}},{"base_weights":[-2.0719804E-2,-1.855459E-1,5.1191732E-2,9.733803E-3,-1.38259325E-2,4.8176874E-4,1.3861614E-2],"categories":[],"categories_nodes":[],"categories_segments":[],"categories_sizes":[],"default_left":[0,0,0,0,0,0,0],"id":42,"left_children":[1,3,5,-1,-1,-1,-1],"loss_changes":[2.7834306E0,2.9962897E0,1.5303135E0,0E0,0E0,0E0,0E0],"parents":[2147483647,0,0,1,1,2,2],"right_children":[2,4,6,-1,-1,-1,-1],"split_conditions":[1E0,7.7E-1,1E0,9.733803E-3,-1.38259325E-2,4.8176874E-4,1.3861614E-2],"split_indices":[10,0,91,0,0,0,0],"split_type":[0,0,0,0,0,0,0],"sum_hessian":[2.1681764E2,6.106062E1,1.5575702E2,9.588007E0,5.147261E1,1.4037593E2,1.5381101E1],"tree_param":{"num_deleted":"0","num_feature":"128","num_nodes":"7","size_leaf_vector":"1"}},{"base_weights":[2.448794E-2,-1.5919542E-1,1.2069382E-1,-1.1968383E-2,1.2413241E-2,-3.7629096E-4,9.776118E-3],"categories":[],"categories_nodes":[],"categories_segments":[],"categories_sizes":[],"default_left":[0,0,0,0,0,0,0],"id":43,"left_children":[1,3,5,-1,-1,-1,-1],"loss_changes":[4.113912E0,3.2270608E0,1.4666722E0,0E0,0E0,0E0,0E0],"parents":[2147483647,0,0,1,1,2,2],"right_children":[2,4,6,-1,-1,-1,-1],"split_conditions":[1E0,4.3E-1,5E0,-1.1968383E-2,1.2413241E-2,-3.7629096E-4,9.776118E-3],"split_indices":[78,11,6,0,0,0,0],"split_type":[0,0,0,0,0,0,0],"sum_hessian":[2.1192746E2,7.059497E1,1.4133249E2,6.2435482E1,8.159486E0,5.5399323E1,8.5933174E1],"tree_param":{"num_deleted":"0","num_feature":"128","num_nodes":"7","size_leaf_vector":"1"}},{"base_weights":[1.3078461E-2,-1.0350689E-1,7.12506E-2,-8.719019E-3,1.1756055E-2,-6.3088336E-3,7.1636997E-3],"categories":[],"categories_nodes":[],"categories_segments":[],"categories_sizes":[],"default_left":[0,0,0,0,0,0,0],"id":44,"left_children":[1,3,5,-1,-1,-1,-1],"loss_changes":[1.5882702E0,2.2918847E0,2.3833842E0,0E0,0E0,0E0,0E0],"parents":[2147483647,0,0,1,1,2,2],"right_children":[2,4,6,-1,-1,-1,-1],"split_conditions":[1E0,4.3E-1,4.58E0,-8.719019E-3,1.1756055E-2,-6.3088336E-3,7.1636997E-3],"split_indices":[78,11,5,0,0,0,0],"split_type":[0,0,0,0,0,0,0],"sum_hessian":[2.1331415E2,6.8412476E1,1.4490167E2,6.058307E1,7.829408E0,3.672203E1,1.08179634E2],"tree_param":{"num_deleted":"0","num_feature":"128","num_nodes":"7","size_leaf_vector":"1"}},{"base_weights":[1.747118E-2,-3.8882382E-2,1.5498564E-1,-3.9241496E-3,8.427342E-3,-3.3589513E-3,1.6667064E-2],"categories":[],"categories_nodes":[],"categories_segments":[],"categories_sizes":[],"default_left":[0,0,0,0,0,0,0],"id":45,"left_children":[1,3,5,-1,-1,-1,-1],"loss_changes":[1.8235806E0,1.52374E0,2.924232E0,0E0,0E0,0E0,0E0],"parents":[2147483647,0,0,1,1,2,2],"right_children":[2,4,6,-1,-1,-1,-1],"split_conditions":[1E0,1E0,1E0,-3.9241496E-3,8.427342E-3,-3.3589513E-3,1.6667064E-2],"split_indices":[80,81,47,0,0,0,0],"split_type":[0,0,0,0,0,0,0],"sum_hessian":[2.1754173E2,1.5939429E2,5.814745E1,1.3906213E2,2.0332153E1,2.8669436E1,2.9478014E1],"tree_param":{"num_deleted":"0","num_feature":"128","num_nodes":"7","size_leaf_vector":"1"}},{"base_weights":[-6.825762E-3,-1.3733897E-1,8.843698E-2,-1.819627E-2,5.454553E-3,9.048271E-3,-3.1333298E-3],"categories":[],"categories_nodes":[],"categories_segments":[],"categories_sizes":[],"default_left":[0,0,0,0,0,0,0],"id":46,"left_children":[1,3,5,-1,-1,-1,-1],"loss_changes":[2.9339612E0,5.945251E0,2.026731E0,0E0,0E0,0E0,0E0],"parents":[2147483647,0,0,1,1,2,2],"right_children":[2,4,6,-1,-1,-1,-1],"split_conditions":[5E0,1E0,1E0,-1.819627E-2,5.454553E-3,9.048271E-3,-3.1333298E-3],"split_indices":[6,81,50,0,0,0,0],"split_type":[0,0,0,0,0,0,0],"sum_hessian":[2.1621188E2,8.93637E1,1.2684818E2,4.407235E1,4.5291355E1,7.744711E1,4.940107E1],"tree_param":{"num_deleted":"0","num_feature":"128","num_nodes":"7","size_leaf_vector":"1"}},{"base_weights":[-1.3789709E-3,-1.4061578E-1,6.250938E-2,-1.534187E-2,5.036018E-3,-4.0753344E-3,7.2286837E-3],"categories":[],"categories_nodes":[],"categories_segments":[],"categories_sizes":[],"default_left":[0,0,0,0,0,0,0],"id":47,"left_children":[1,3,5,-1,-1,-1,-1],"loss_changes":[2.083771E0,3.2634E0,2.0173125E0,0E0,0E0,0E0,0E0],"parents":[2147483647,0,0,1,1,2,2],"right_children":[2,4,6,-1,-1,-1,-1],"split_conditions":[1E0,1E0,1.7E-1,-1.534187E-2,5.036018E-3,-4.0753344E-3,7.2286837E-3],"split_indices":[10,50,11,0,0,0,0],"split_type":[0,0,0,0,0,0,0],"sum_hessian":[2.1436604E2,6.364657E1,1.5071948E2,3.608128E1,2.7565289E1,5.4733913E1,9.5985565E1],"tree_param":{"num_deleted":"0","num_feature":"128","num_nodes":"7","size_leaf_vector":"1"}},{"base_weights":[-1.6520137E-2,-1.4245799E-1,4.3156307E-2,-1.9349437E-2,-3.9229472E-4,-3.9399783E-3,6.0325502E-3],"categories":[],"categories_nodes":[],"categories_segments":[],"categories_sizes":[],"default_left":[0,0,0,0,0,0,0],"id":48,"left_children":[1,3,5,-1,-1,-1,-1],"loss_changes":[1.7176923E0,2.3783712E0,1.5807194E0,0E0,0E0,0E0,0E0],"parents":[2147483647,0,0,1,1,2,2],"right_children":[2,4,6,-1,-1,-1,-1],"split_conditions":[1E0,1E0,5E0,-1.9349437E-2,-3.9229472E-4,-3.9399783E-3,6.0325502E-3],"split_indices":[10,47,6,0,0,0,0],"split_type":[0,0,0,0,0,0,0],"sum_hessian":[2.1037222E2,6.317644E1,1.4719579E2,1.5773863E1,4.7402576E1,5.7126152E1,9.006963E1],"tree_param":{"num_deleted":"0","num_feature":"128","num_nodes":"7","size_leaf_vector":"1"}},{"base_weights":[-1.1805116E-3,-2.0554337E-1,3.499036E-2,-8.604592E-4,-1.5000026E-2,-2.5581036E-4,1.1820637E-2],"categories":[],"categories_nodes":[],"categories_segments":[],"categories_sizes":[],"default_left":[0,0,0,0,0,0,0],"id":49,"left_children":[1,3,5,-1,-1,-1,-1],"loss_changes":[1.7660444E0,5.873506E-1,1.6541445E0,0E0,0E0,0E0,0E0],"parents":[2147483647,0,0,1,1,2,2],"right_children":[2,4,6,-1,-1,-1,-1],"split_conditions":[-1.7E-1,1E0,1E0,-8.604592E-4,-1.5000026E-2,-2.5581036E-4,1.1820637E-2],"split_indices":[11,35,91,0,0,0,0],"split_type":[0,0,0,0,0,0,0],"sum_hessian":[2.1918399E2,2.5918821E1,1.9326517E2,1.260605E1,1.3312772E1,1.6930058E2,2.3964584E1],"tree_param":{"num_deleted":"0","num_feature":"128","num_nodes":"7","size_leaf_vector":"1"}},{"base_weights":[-6.5159136E-3,-1.5692392E-1,6.259247E-2,1.0362072E-2,-1.1858356E-2,7.4684485E-3,-3.4802097E-3],"categories":[],"categories_nodes":[],"categories_segments":[],"categories_sizes":[],"default_left":[0,0,0,0,0,0,0],"id":50,"left_children":[1,3,5,-1,-1,-1,-1],"loss_changes":[2.430952E0,2.6394186E0,1.9499354E0,0E0,0E0,0E0,0E0],"parents":[2147483647,0,0,1,1,2,2],"right_children":[2,4,6,-1,-1,-1,-1],"split_conditions":[1E0,7.7E-1,1E0,1.0362072E-2,-1.1858356E-2,7.4684485E-3,-3.4802097E-3],"split_indices":[10,0,50,0,0,0,0],"split_type":[0,0,0,0,0,0,0],"sum_hessian":[2.1442058E2,6.35037E1,1.5091687E2,8.60865E0,5.489505E1,9.032606E1,6.0590813E1],"tree_param":{"num_deleted":"0","num_feature":"128","num_nodes":"7","size_leaf_vector":"1"}},{"base_weights":[1.626855E-2,-1.1947225E-1,1.1462439E-1,-1.450131E-2,3.909991E-3,1.2357264E-2,-4.042678E-3],"categories":[],"categories_nodes":[],"categories_segments":[],"categories_sizes":[],"default_left":[0,0,0,0,0,0,0],"id":51,"left_children":[1,3,5,-1,-1,-1,-1],"loss_changes":[3.1283915E0,3.5657015E0,3.6976767E0,0E0,0E0,0E0,0E0],"parents":[2147483647,0,0,1,1,2,2],"right_children":[2,4,6,-1,-1,-1,-1],"split_conditions":[1.7E-1,1E0,1E0,-1.450131E-2,3.909991E-3,1.2357264E-2,-4.042678E-3],"split_indices":[11,81,15,0,0,0,0],"split_type":[0,0,0,0,0,0,0],"sum_hessian":[2.1406332E2,8.903679E1,1.25026535E2,4.5288887E1,4.3747902E1,7.293701E1,5.208952E1],"tree_param":{"num_deleted":"0","num_feature":"128","num_nodes":"7","size_leaf_vector":"1"}},{"base_weights":[-4.160832E-3,-1.425077E-1,5.635303E-2,-2.1401998E-2,-1.2373407E-3,-5.139056E-4,1.2810809E-2],"categories":[],"categories_nodes":[],"categories_segments":[],"categories_sizes":[],"default_left":[0,0,0,0,0,0,0],"id":52,"left_children":[1,3,5,-1,-1,-1,-1],"loss_changes":[2.038777E0,2.3829763E0,2.2890868E0,0E0,0E0,0E0,0E0],"parents":[2147483647,0,0,1,1,2,2],"right_children":[2,4,6,-1,-1,-1,-1],"split_conditions":[1E0,1E0,1E0,-2.1401998E-2,-1.2373407E-3,-5.139056E-4,1.2810809E-2],"split_indices":[10,42,80,0,0,0,0],"split_type":[0,0,0,0,0,0,0],"sum_hessian":[2.2393364E2,6.402044E1,1.5991321E2,1.1000219E1,5.3020218E1,1.27044395E2,3.2868805E1],"tree_param":{"num_deleted":"0","num_feature":"128","num_nodes":"7","size_leaf_vector":"1"}},{"base_weights":[-1.5693117E-2,-1.5315044E-1,8.427716E-2,-1.8144432E-2,3.4810149E-3,1.1330652E-2,-3.215557E-3],"categories":[],"categories_nodes":[],"categories_segments":[],"categories_sizes":[],"default_left":[0,0,0,0,0,0,0],"id":53,"left_children":[1,3,5,-1,-1,-1,-1],"loss_changes":[3.1894028E0,4.799815E0,3.0090363E0,0E0,0E0,0E0,0E0],"parents":[2147483647,0,0,1,1,2,2],"right_children":[2,4,6,-1,-1,-1,-1],"split_conditions":[5E0,1E0,1E0,-1.8144432E-2,3.4810149E-3,1.1330652E-2,-3.215557E-3],"split_indices":[6,47,47,0,0,0,0],"split_type":[0,0,0,0,0,0,0],"sum_hessian":[2.1270488E2,8.7320786E1,1.25384094E2,4.1736332E1,4.5584457E1,6.1357437E1,6.402666E1],"tree_param":{"num_deleted":"0","num_feature":"128","num_nodes":"7","size_leaf_vector":"1"}},{"base_weights":[8.972857E-3,-1.23390846E-1,9.979469E-2,-1.625075E-2,4.2568194E-3,1.0661247E-2,-7.652828E-4],"categories":[],"categories_nodes":[],"categories_segments":[],"categories_sizes":[],"default_left":[0,0,0,0,0,0,0],"id":54,"left_children":[1,3,5,-1,-1,-1,-1],"loss_changes":[2.8962495E0,4.411434E0,1.8909607E0,0E0,0E0,0E0,0E0],"parents":[2147483647,0,0,1,1,2,2],"right_children":[2,4,6,-1,-1,-1,-1],"split_conditions":[5E0,1E0,1E0,-1.625075E-2,4.2568194E-3,1.0661247E-2,-7.652828E-4],"split_indices":[6,47,47,0,0,0,0],"split_type":[0,0,0,0,0,0,0],"sum_hessian":[2.206791E2,8.83426E1,1.323365E2,4.207461E1,4.626799E1,6.2358093E1,6.99784E1],"tree_param":{"num_deleted":"0","num_feature":"128","num_nodes":"7","size_leaf_vector":"1"}},{"base_weights":[3.0293611E-3,-1.10078365E-1,8.1009395E-2,-1.453946E-2,5.0069117E-3,-8.060208E-3,8.043739E-3],"categories":[],"categories_nodes":[],"categories_segments":[],"categories_sizes":[],"default_left":[0,0,0,0,0,0,0],"id":55,"left_children":[1,3,5,-1,-1,-1,-1],"loss_changes":[2.0740197E0,3.9408517E0,2.9474947E0,0E0,0E0,0E0,0E0],"parents":[2147483647,0,0,1,1,2,2],"right_children":[2,4,6,-1,-1,-1,-1],"split_conditions":[5E0,1E0,1E0,-1.453946E-2,5.0069117E-3,-8.060208E-3,8.043739E-3],"split_indices":[6,81,10,0,0,0,0],"split_type":[0,0,0,0,0,0,0],"sum_hessian":[2.1503554E2,8.607299E1,1.2896255E2,4.4223667E1,4.184932E1,2.9453203E1,9.9509346E1],"tree_param":{"num_deleted":"0","num_feature":"128","num_nodes":"7","size_leaf_vector":"1"}},{"base_weights":[-4.4334754E-3,-6.4941354E-2,2.3198186E-1,-7.952834E-3,2.1829128E-3,1.701384E-2,-6.5171192E-3],"categories":[],"categories_nodes":[],"categories_segments":[],"categories_sizes":[],"default_left":[0,0,0,0,0,0,0],"id":56,"left_children":[1,3,5,-1,-1,-1,-1],"loss_changes":[3.3506708E0,1.9697716E0,2.3180478E0,0E0,0E0,0E0,0E0],"parents":[2147483647,0,0,1,1,2,2],"right_children":[2,4,6,-1,-1,-1,-1],"split_conditions":[4.3E-1,1E0,1E0,-7.952834E-3,2.1829128E-3,1.701384E-2,-6.5171192E-3],"split_indices":[11,9,82,0,0,0,0],"split_type":[0,0,0,0,0,0,0],"sum_hessian":[2.1369948E2,1.759262E2,3.7773273E1,9.175914E1,8.416706E1,2.9549679E1,8.223593E0],"tree_param":{"num_deleted":"0","num_feature":"128","num_nodes":"7","size_leaf_vector":"1"}},{"base_weights":[8.679851E-3,-1.6232093E-1,1.2797052E-1,-1.8162256E-2,4.3139453E-3,1.2311259E-2,-3.416177E-4],"categories":[],"categories_nodes":[],"categories_segments":[],"categories_sizes":[],"default_left":[0,0,0,0,0,0,0],"id":57,"left_children":[1,3,5,-1,-1,-1,-1],"loss_changes":[4.8126545E0,5.167257E0,2.225784E0,0E0,0E0,0E0,0E0],"parents":[2147483647,0,0,1,1,2,2],"right_children":[2,4,6,-1,-1,-1,-1],"split_conditions":[5E0,1E0,1E0,-1.8162256E-2,4.3139453E-3,1.2311259E-2,-3.416177E-4],"split_indices":[6,81,47,0,0,0,0],"split_type":[0,0,0,0,0,0,0],"sum_hessian":[2.1574527E2,8.717478E1,1.2857048E2,4.5659817E1,4.1514965E1,6.408601E1,6.448447E1],"tree_param":{"num_deleted":"0","num_feature":"128","num_nodes":"7","size_leaf_vector":"1"}},{"base_weights":[2.2514863E-2,-1.2956233E-1,8.513809E-2,-2.1233825E-2,1.4998604E-3,-3.491185E-3,7.918513E-3],"categories":[],"categories_nodes":[],"categories_segments":[],"categories_sizes":[],"default_left":[0,0,0,0,0,0,0],"id":58,"left_children":[1,3,5,-1,-1,-1,-1],"loss_changes":[2.3234675E0,3.5058663E0,2.0470371E0,0E0,0E0,0E0,0E0],"parents":[2147483647,0,0,1,1,2,2],"right_children":[2,4,6,-1,-1,-1,-1],"split_conditions":[1E0,1E0,5E0,-2.1233825E-2,1.4998604E-3,-3.491185E-3,7.918513E-3],"split_indices":[10,47,6,0,0,0,0],"split_type":[0,0,0,0,0,0,0],"sum_hessian":[2.2238786E2,6.1747684E1,1.6064017E2,1.5838307E1,4.5909378E1,5.1702137E1,1.08938034E2],"tree_param":{"num_deleted":"0","num_feature":"128","num_nodes":"7","size_leaf_vector":"1"}},{"base_weights":[-2.6852863E-2,-1.2724671E-1,8.205775E-2,-1.0836387E-2,3.6464974E-3,6.4850636E-3,-1.1519676E-2],"categories":[],"categories_nodes":[],"categories_segments":[],"categories_sizes":[],"default_left":[0,0,0,0,0,0,0],"id":59,"left_children":[1,3,5,-1,-1,-1,-1],"loss_changes":[2.610843E0,2.3648376E0,2.026113E0,0E0,0E0,0E0,0E0],"parents":[2147483647,0,0,1,1,2,2],"right_children":[2,4,6,-1,-1,-1,-1],"split_conditions":[1E0,1E0,1E0,-1.0836387E-2,3.6464974E-3,6.4850636E-3,-1.1519676E-2],"split_indices":[79,80,124,0,0,0,0],"split_type":[0,0,0,0,0,0,0],"sum_hessian":[2.1923334E2,1.1320101E2,1.0603233E2,7.765956E1,3.5541447E1,9.707843E1,8.953903E0],"tree_param":{"num_deleted":"0","num_feature":"128","num_nodes":"7","size_leaf_vector":"1"}},{"base_weights":[-2.3691634E-2,-1.7665517E-1,4.408961E-2,-2.3768356E-2,-2.1773211E-3,-5.84737E-3,6.346948E-3],"categories":[],"categories_nodes":[],"categories_segments":[],"categories_sizes":[],"default_left":[0,0,0,0,0,0,0],"id":60,"left_children":[1,3,5,-1,-1,-1,-1],"loss_changes":[2.5368526E0,2.7679753E0,2.447862E0,0E0,0E0,0E0,0E0],"parents":[2147483647,0,0,1,1,2,2],"right_children":[2,4,6,-1,-1,-1,-1],"split_conditions":[1E0,1E0,5E0,-2.3768356E-2,-2.1773211E-3,-5.84737E-3,6.346948E-3],"split_indices":[10,42,6,0,0,0,0],"split_type":[0,0,0,0,0,0,0],"sum_hessian":[2.2716743E2,6.482124E1,1.6234619E2,1.2055216E1,5.2766026E1,5.375165E1,1.08594536E2],"tree_param":{"num_deleted":"0","num_feature":"128","num_nodes":"7","size_leaf_vector":"1"}},{"base_weights":[-1.7688962E-2,-1.2728387E-1,5.639135E-2,-1.7282275E-2,3.8944178E-3,8.483648E-3,-3.4190156E-3],"categories":[],"categories_nodes":[],"categories_segments":[],"categories_sizes":[],"default_left":[0,0,0,0,0,0,0],"id":61,"left_children":[1,3,5,-1,-1,-1,-1],"loss_changes":[1.9516991E0,4.590788E0,2.1667898E0,0E0,0E0,0E0,0E0],"parents":[2147483647,0,0,1,1,2,2],"right_children":[2,4,6,-1,-1,-1,-1],"split_conditions":[5E0,1E0,1E0,-1.7282275E-2,3.8944178E-3,8.483648E-3,-3.4190156E-3],"split_indices":[6,47,47,0,0,0,0],"split_type":[0,0,0,0,0,0,0],"sum_hessian":[2.2155103E2,8.645986E1,1.3509117E2,3.8566994E1,4.7892864E1,6.89196E1,6.617157E1],"tree_param":{"num_deleted":"0","num_feature":"128","num_nodes":"7","size_leaf_vector":"1"}},{"base_weights":[-2.7411238E-3,-9.5331214E-2,1.1180088E-1,-1.4053482E-2,1.9802547E-3,-1.1570249E-3,1.2812354E-2],"categories":[],"categories_nodes":[],"categories_segments":[],"categories_sizes":[],"default_left":[0,0,0,0,0,0,0],"id":62,"left_children":[1,3,5,-1,-1,-1,-1],"loss_changes":[2.5806665E0,3.4798014E0,2.1816149E0,0E0,0E0,0E0,0E0],"parents":[2147483647,0,0,1,1,2,2],"right_children":[2,4,6,-1,-1,-1,-1],"split_conditions":[1E0,5E0,1E0,-1.4053482E-2,1.9802547E-3,-1.1570249E-3,1.2812354E-2],"split_indices":[79,6,9,0,0,0,0],"split_type":[0,0,0,0,0,0,0],"sum_hessian":[2.2328423E2,1.24401436E2,9.888278E1,4.7789665E1,7.661177E1,5.5465237E1,4.3417545E1],"tree_param":{"num_deleted":"0","num_feature":"128","num_nodes":"7","size_leaf_vector":"1"}},{"base_weights":[-8.090727E-3,-4.182926E-2,2.0988616E-1,-9.857763E-3,1.071724E-3,-1.2795839E-3,1.5310581E-2],"categories":[],"categories_nodes":[],"categories_segments":[],"categories_sizes":[],"default_left":[0,0,0,0,0,0,0],"id":63,"left_children":[1,3,5,-1,-1,-1,-1],"loss_changes":[1.7832747E0,2.086E0,8.169701E-1,0E0,0E0,0E0,0E0],"parents":[2147483647,0,0,1,1,2,2],"right_children":[2,4,6,-1,-1,-1,-1],"split_conditions":[1E0,1E0,2.2E-1,-9.857763E-3,1.071724E-3,-1.2795839E-3,1.5310581E-2],"split_indices":[93,10,3,0,0,0,0],"split_type":[0,0,0,0,0,0,0],"sum_hessian":[2.2054529E2,1.9798251E2,2.2562775E1,5.1174404E1,1.4680812E2,8.681974E0,1.38808E1],"tree_param":{"num_deleted":"0","num_feature":"128","num_nodes":"7","size_leaf_vector":"1"}},{"base_weights":[9.013683E-3,-8.920868E-2,1.3052921E-1,2.844323E-3,-9.853038E-3,-3.4548652E-3,1.0038358E-2],"categories":[],"categories_nodes":[],"categories_segments":[],"categories_sizes":[],"default_left":[0,0,0,0,0,0,0],"id":64,"left_children":[1,3,5,-1,-1,-1,-1],"loss_changes":[2.880448E0,2.2235436E0,1.6470655E0,0E0,0E0,0E0,0E0],"parents":[2147483647,0,0,1,1,2,2],"right_children":[2,4,6,-1,-1,-1,-1],"split_conditions":[1E0,1E0,1E0,2.844323E-3,-9.853038E-3,-3.4548652E-3,1.0038358E-2],"split_indices":[79,29,29,0,0,0,0],"split_type":[0,0,0,0,0,0,0],"sum_hessian":[2.2157767E2,1.2400317E2,9.757449E1,5.4671417E1,6.933175E1,2.5438103E1,7.213639E1],"tree_param":{"num_deleted":"0","num_feature":"128","num_nodes":"7","size_leaf_vector":"1"}},{"base_weights":[1.5286081E-2,-1.6584419E-1,6.235785E-2,-1.249422E-2,8.98594E-3,2.5143227E-4,1.134058E-2],"categories":[],"categories_nodes":[],"categories_segments":[],"categories_sizes":[],"default_left":[0,0,0,0,0,0,0],"id":65,"left_children":[1,3,5,-1,-1,-1,-1],"loss_changes":[2.0533776E0,1.8984754E0,1.7685671E0,0E0,0E0,0E0,0E0],"parents":[2147483647,0,0,1,1,2,2],"right_children":[2,4,6,-1,-1,-1,-1],"split_conditions":[-1.2E-1,1E0,1E0,-1.249422E-2,8.98594E-3,2.5143227E-4,1.134058E-2],"split_indices":[11,89,80,0,0,0,0],"split_type":[0,0,0,0,0,0,0],"sum_hessian":[2.187043E2,3.9907948E1,1.7879636E2,3.432818E1,5.579768E0,1.4022067E2,3.8575687E1],"tree_param":{"num_deleted":"0","num_feature":"128","num_nodes":"7","size_leaf_vector":"1"}},{"base_weights":[-2.5170424E-3,-1.9889298E-1,4.8155848E-2,-1.371052E-2,7.86122E-3,1.1605657E-2,-3.9273757E-4],"categories":[],"categories_nodes":[],"categories_segments":[],"categories_sizes":[],"default_left":[0,0,0,0,0,0,0],"id":66,"left_children":[1,3,5,-1,-1,-1,-1],"loss_changes":[2.4315991E0,1.7747968E0,2.0236917E0,0E0,0E0,0E0,0E0],"parents":[2147483647,0,0,1,1,2,2],"right_children":[2,4,6,-1,-1,-1,-1],"split_conditions":[-1.2E-1,1E0,1E0,-1.371052E-2,7.86122E-3,1.1605657E-2,-3.9273757E-4],"split_indices":[11,89,45,0,0,0,0],"split_type":[0,0,0,0,0,0,0],"sum_hessian":[2.2473373E2,4.009615E1,1.8463759E2,3.4994873E1,5.1012764E0,3.575744E1,1.4888014E2],"tree_param":{"num_deleted":"0","num_feature":"128","num_nodes":"7","size_leaf_vector":"1"}},{"base_weights":[5.007311E-3,-2.0651941E-1,5.825946E-2,-1.4790299E-2,1.4517846E-3,-1.8673464E-4,1.03314975E-2],"categories":[],"categories_nodes":[],"categories_segments":[],"categories_sizes":[],"default_left":[0,0,0,0,0,0,0],"id":67,"left_children":[1,3,5,-1,-1,-1,-1],"loss_changes":[2.7479885E0,1.118902E0,1.7936094E0,0E0,0E0,0E0,0E0],"parents":[2147483647,0,0,1,1,2,2],"right_children":[2,4,6,-1,-1,-1,-1],"split_conditions":[-1.2E-1,1E0,4.64E0,-1.4790299E-2,1.4517846E-3,-1.8673464E-4,1.03314975E-2],"split_indices":[11,45,5,0,0,0,0],"split_type":[0,0,0,0,0,0,0],"sum_hessian":[2.2327524E2,3.9116467E1,1.8415877E2,2.6510067E1,1.2606401E1,1.3676292E2,4.7395844E1],"tree_param":{"num_deleted":"0","num_feature":"128","num_nodes":"7","size_leaf_vector":"1"}},{"base_weights":[6.2895785E-3,-1.5448769E-2,2.9582977E-2,-2.5096464E-5,1.2447609E-2],"categories":[],"categories_nodes":[],"categories_segments":[],"categories_sizes":[],"default_left":[0,0,0,0,0],"id":68,"left_children":[1,-1,3,-1,-1],"loss_changes":[1.8259624E0,0E0,1.5130794E0,0E0,0E0],"parents":[2147483647,0,0,2,2],"right_children":[2,-1,4,-1,-1],"split_conditions":[1E0,-1.5448769E-2,1E0,-2.5096464E-5,1.2447609E-2],"split_indices":[20,0,93,0,0],"split_type":[0,0,0,0,0],"sum_hessian":[2.2620026E2,7.1247787E0,2.1907549E2,2.0142818E2,1.7647305E1],"tree_param":{"num_deleted":"0","num_feature":"128","num_nodes":"5","size_leaf_vector":"1"}},{"base_weights":[-8.945927E-3,-7.803298E-2,8.656512E-2,-1.245693E-2,9.688508E-4,1.1387364E-2,-3.0815226E-4],"categories":[],"categories_nodes":[],"categories_segments":[],"categories_sizes":[],"default_left":[0,0,0,0,0,0,0],"id":69,"left_children":[1,3,5,-1,-1,-1,-1],"loss_changes":[1.621548E0,2.413635E0,1.3701885E0,0E0,0E0,0E0,0E0],"parents":[2147483647,0,0,1,1,2,2],"right_children":[2,4,6,-1,-1,-1,-1],"split_conditions":[1E0,1.7E-1,2E-1,-1.245693E-2,9.688508E-4,1.1387364E-2,-3.0815226E-4],"split_indices":[79,11,3,0,0,0,0],"split_type":[0,0,0,0,0,0,0],"sum_hessian":[2.2550511E2,1.3191531E2,9.35898E1,4.2204563E1,8.9710754E1,3.1329185E1,6.2260612E1],"tree_param":{"num_deleted":"0","num_feature":"128","num_nodes":"7","size_leaf_vector":"1"}},{"base_weights":[-1.0735003E-2,-3.5823423E-2,2.574128E-1,-3.1561498E-3,1.13668805E-2,2.191315E-3,1.4849767E-2],"categories":[],"categories_nodes":[],"categories_segments":[],"categories_sizes":[],"default_left":[0,0,0,0,0,0,0],"id":70,"left_children":[1,3,5,-1,-1,-1,-1],"loss_changes":[1.689596E0,1.766462E0,5.1915407E-2,0E0,0E0,0E0,0E0],"parents":[2147483647,0,0,1,1,2,2],"right_children":[2,4,6,-1,-1,-1,-1],"split_conditions":[1E0,1E0,1E0,-3.1561498E-3,1.13668805E-2,2.191315E-3,1.4849767E-2],"split_indices":[100,102,50,0,0,0,0],"split_type":[0,0,0,0,0,0,0],"sum_hessian":[2.2744402E2,2.1590735E2,1.1536663E1,2.0250175E2,1.3405597E1,5.098331E0,6.4383326E0],"tree_param":{"num_deleted":"0","num_feature":"128","num_nodes":"7","size_leaf_vector":"1"}},{"base_weights":[-3.468552E-3,-4.3057207E-2,2.6640227E-1,-4.6762084E-3,6.485595E-3,1.835192E-2,-7.5493654E-4],"categories":[],"categories_nodes":[],"categories_segments":[],"categories_sizes":[],"default_left":[0,0,0,0,0,0,0],"id":71,"left_children":[1,3,5,-1,-1,-1,-1],"loss_changes":[2.624282E0,1.9824444E0,9.461186E-1,0E0,0E0,0E0,0E0],"parents":[2147483647,0,0,1,1,2,2],"right_children":[2,4,6,-1,-1,-1,-1],"split_conditions":[1E0,4.3E-1,4.4E0,-4.6762084E-3,6.485595E-3,1.835192E-2,-7.5493654E-4],"split_indices":[93,11,2,0,0,0,0],"split_type":[0,0,0,0,0,0,0],"sum_hessian":[2.2489497E2,2.0345387E2,2.1441109E1,1.610089E2,4.244497E1,1.355618E1,7.8849287E0],"tree_param":{"num_deleted":"0","num_feature":"128","num_nodes":"7","size_leaf_vector":"1"}},{"base_weights":[2.7430767E-2,-8.429806E-3,2.4079654E-1,-2.773576E-3,7.5442493E-3,1.5773928E-2,-2.7402323E-3],"categories":[],"categories_nodes":[],"categories_segments":[],"categories_sizes":[],"default_left":[0,0,0,0,0,0,0],"id":72,"left_children":[1,3,5,-1,-1,-1,-1],"loss_changes":[1.7617835E0,1.6164268E0,9.03339E-1,0E0,0E0,0E0,0E0],"parents":[2147483647,0,0,1,1,2,2],"right_children":[2,4,6,-1,-1,-1,-1],"split_conditions":[1E0,1E0,1E0,-2.773576E-3,7.5442493E-3,1.5773928E-2,-2.7402323E-3],"split_indices":[93,85,35,0,0,0,0],"split_type":[0,0,0,0,0,0,0],"sum_hessian":[2.1760286E2,1.945154E2,2.3087461E1,1.5520525E2,3.9310146E1,1.789416E1,5.1933017E0],"tree_param":{"num_deleted":"0","num_feature":"128","num_nodes":"7","size_leaf_vector":"1"}},{"base_weights":[7.765191E-3,-2.3142193E-2,2.1777792E-1,-8.0362735E-3,1.4766434E-3,1.5218335E-2,4.4728207E-5],"categories":[],"categories_nodes":[],"categories_segments":[],"categories_sizes":[],"default_left":[0,0,0,0,0,0,0],"id":73,"left_children":[1,3,5,-1,-1,-1,-1],"loss_changes":[1.5275468E0,1.5506479E0,5.635849E-1,0E0,0E0,0E0,0E0],"parents":[2147483647,0,0,1,1,2,2],"right_children":[2,4,6,-1,-1,-1,-1],"split_conditions":[1E0,1E0,4.4E0,-8.0362735E-3,1.4766434E-3,1.5218335E-2,4.4728207E-5],"split_indices":[93,10,2,0,0,0,0],"split_type":[0,0,0,0,0,0,0],"sum_hessian":[2.175706E2,1.9741524E2,2.0155363E1,4.8977386E1,1.4843785E2,1.1521749E1,8.6336155E0],"tree_param":{"num_deleted":"0","num_feature":"128","num_nodes":"7","size_leaf_vector":"1"}},{"base_weights":[1.5894253E-2,-1.0742203E-1,8.2713604E-2,-1.5633194E-2,2.6366257E-3,9.397155E-3,-2.8707758E-3],"categories":[],"categories_nodes":[],"categories_segments":[],"categories_sizes":[],"default_left":[0,0,0,0,0,0,0],"id":74,"left_children":[1,3,5,-1,-1,-1,-1],"loss_changes":[2.0154018E0,3.008725E0,2.427261E0,0E0,0E0,0E0,0E0],"parents":[2147483647,0,0,1,1,2,2],"right_children":[2,4,6,-1,-1,-1,-1],"split_conditions":[1.7E-1,1E0,1E0,-1.5633194E-2,2.6366257E-3,9.397155E-3,-2.8707758E-3],"split_indices":[11,47,47,0,0,0,0],"split_type":[0,0,0,0,0,0,0],"sum_hessian":[2.2380695E2,7.6517E1,1.4728995E2,2.9363869E1,4.7153126E1,8.217145E1,6.51185E1],"tree_param":{"num_deleted":"0","num_feature":"128","num_nodes":"7","size_leaf_vector":"1"}},{"base_weights":[1.6687802E-3,-2.4481053E-2,1.712641E-1,-9.310012E-3,9.048354E-4,1.2725067E-2,-4.270434E-3],"categories":[],"categories_nodes":[],"categories_segments":[],"categories_sizes":[],"default_left":[0,0,0,0,0,0,0],"id":75,"left_children":[1,3,5,-1,-1,-1,-1],"loss_changes":[1.095737E0,1.5115176E0,9.222815E-1,0E0,0E0,0E0,0E0],"parents":[2147483647,0,0,1,1,2,2],"right_children":[2,4,6,-1,-1,-1,-1],"split_conditions":[1E0,-1E-1,1E0,-9.310012E-3,9.048354E-4,1.2725067E-2,-4.270434E-3],"split_indices":[93,11,35,0,0,0,0],"split_type":[0,0,0,0,0,0,0],"sum_hessian":[2.2761806E2,2.0462372E2,2.2994345E1,3.561578E1,1.6900793E2,1.7427368E1,5.566977E0],"tree_param":{"num_deleted":"0","num_feature":"128","num_nodes":"7","size_leaf_vector":"1"}},{"base_weights":[6.8935296E-3,-1.8302398E-2,2.488856E-1,-8.912472E-3,2.1767914E-3,4.8681707E-4,1.6190829E-2],"categories":[],"categories_nodes":[],"categories_segments":[],"categories_sizes":[],"default_left":[0,0,0,0,0,0,0],"id":76,"left_children":[1,3,5,-1,-1,-1,-1],"loss_changes":[1.4717467E0,2.2651248E0,3.760146E-1,0E0,0E0,0E0,0E0],"parents":[2147483647,0,0,1,1,2,2],"right_children":[2,4,6,-1,-1,-1,-1],"split_conditions":[1E0,1E0,1E0,-8.912472E-3,2.1767914E-3,4.8681707E-4,1.6190829E-2],"split_indices":[100,10,50,0,0,0,0],"split_type":[0,0,0,0,0,0,0],"sum_hessian":[2.2390923E2,2.111665E2,1.2742726E1,5.3628677E1,1.5753783E2,5.7357883E0,7.0069385E0],"tree_param":{"num_deleted":"0","num_feature":"128","num_nodes":"7","size_leaf_vector":"1"}},{"base_weights":[5.265788E-4,-5.855393E-2,9.323081E-2,-6.1314446E-3,5.142124E-3,-3.6514425E-3,7.824609E-3],"categories":[],"categories_nodes":[],"categories_segments":[],"categories_sizes":[],"default_left":[0,0,0,0,0,0,0],"id":77,"left_children":[1,3,5,-1,-1,-1,-1],"loss_changes":[1.3497066E0,1.6831813E0,1.122929E0,0E0,0E0,0E0,0E0],"parents":[2147483647,0,0,1,1,2,2],"right_children":[2,4,6,-1,-1,-1,-1],"split_conditions":[1E0,1E0,1E0,-6.1314446E-3,5.142124E-3,-3.6514425E-3,7.824609E-3],"split_indices":[79,80,29,0,0,0,0],"split_type":[0,0,0,0,0,0,0],"sum_hessian":[2.2646402E2,1.4056535E2,8.589867E1,1.0233857E2,3.8226776E1,2.3250126E1,6.264854E1],"tree_param":{"num_deleted":"0","num_feature":"128","num_nodes":"7","size_leaf_vector":"1"}},{"base_weights":[5.2319877E-3,-2.614393E-2,2.060864E-1,-8.561513E-3,1.2926314E-3,1.6435688E-2,-2.298212E-3],"categories":[],"categories_nodes":[],"categories_segments":[],"categories_sizes":[],"default_left":[0,0,0,0,0,0,0],"id":78,"left_children":[1,3,5,-1,-1,-1,-1],"loss_changes":[1.5418866E0,1.6518182E0,1.1718935E0,0E0,0E0,0E0,0E0],"parents":[2147483647,0,0,1,1,2,2],"right_children":[2,4,6,-1,-1,-1,-1],"split_conditions":[1E0,1E0,4.4E0,-8.561513E-3,1.2926314E-3,1.6435688E-2,-2.298212E-3],"split_indices":[93,10,2,0,0,0,0],"split_type":[0,0,0,0,0,0,0],"sum_hessian":[2.26117E2,2.030902E2,2.3026812E1,4.753154E1,1.5555865E2,1.3444321E1,9.582492E0],"tree_param":{"num_deleted":"0","num_feature":"128","num_nodes":"7","size_leaf_vector":"1"}},{"base_weights":[6.8808394E-3,-1.56672E-2,3.073188E-2,-6.123754E-4,8.645142E-3],"categories":[],"categories_nodes":[],"categories_segments":[],"categories_sizes":[],"default_left":[0,0,0,0,0],"id":79,"left_children":[1,-1,3,-1,-1],"loss_changes":[1.9220691E0,0E0,1.4362508E0,0E0,0E0],"parents":[2147483647,0,0,2,2],"right_children":[2,-1,4,-1,-1],"split_conditions":[1E0,-1.56672E-2,1E0,-6.123754E-4,8.645142E-3],"split_indices":[20,0,80,0,0],"split_type":[0,0,0,0,0],"sum_hessian":[2.2904758E2,7.46374E0,2.2158383E2,1.7716425E2,4.441959E1],"tree_param":{"num_deleted":"0","num_feature":"128","num_nodes":"5","size_leaf_vector":"1"}},{"base_weights":[-3.1073483E-2,-6.0315747E-2,1.7924242E-1,-4.89614E-3,8.2232645E-3,1.4032579E-2,-3.4365847E-3],"categories":[],"categories_nodes":[],"categories_segments":[],"categories_sizes":[],"default_left":[0,0,0,0,0,0,0],"id":80,"left_children":[1,3,5,-1,-1,-1,-1],"loss_changes":[1.5261719E0,1.9355025E0,9.639862E-1,0E0,0E0,0E0,0E0],"parents":[2147483647,0,0,1,1,2,2],"right_children":[2,4,6,-1,-1,-1,-1],"split_conditions":[1E0,1E0,4.4E0,-4.89614E-3,8.2232645E-3,1.4032579E-2,-3.4365847E-3],"split_indices":[93,83,2,0,0,0,0],"split_type":[0,0,0,0,0,0,0],"sum_hessian":[2.2057472E2,1.9991124E2,2.066347E1,1.760935E2,2.3817738E1,1.3730567E1,6.932901E0],"tree_param":{"num_deleted":"0","num_feature":"128","num_nodes":"7","size_leaf_vector":"1"}},{"base_weights":[-1.4010681E-2,-7.259917E-2,2.2650994E-1,-6.5145493E-3,5.4977327E-3,1.9147225E-2,-1.3030232E-3],"categories":[],"categories_nodes":[],"categories_segments":[],"categories_sizes":[],"default_left":[0,0,0,0,0,0,0],"id":81,"left_children":[1,3,5,-1,-1,-1,-1],"loss_changes":[3.3977985E0,2.1662116E0,1.9714653E0,0E0,0E0,0E0,0E0],"parents":[2147483647,0,0,1,1,2,2],"right_children":[2,4,6,-1,-1,-1,-1],"split_conditions":[1E0,1E0,1E0,-6.5145493E-3,5.4977327E-3,1.9147225E-2,-1.3030232E-3],"split_indices":[83,80,45,0,0,0,0],"split_type":[0,0,0,0,0,0,0],"sum_hessian":[2.1945029E2,1.8207915E2,3.7371136E1,1.4053064E2,4.15485E1,1.9889984E1,1.748115E1],"tree_param":{"num_deleted":"0","num_feature":"128","num_nodes":"7","size_leaf_vector":"1"}},{"base_weights":[-4.0888125E-3,-1.3869728E-1,4.97666E-2,1.0208932E-2,-1.1409456E-2,-7.1159587E-3,6.226219E-3],"categories":[],"categories_nodes":[],"categories_segments":[],"categories_sizes":[],"default_left":[0,0,0,0,0,0,0],"id":82,"left_children":[1,3,5,-1,-1,-1,-1],"loss_changes":[1.8015293E0,2.6424718E0,2.7340436E0,0E0,0E0,0E0,0E0],"parents":[2147483647,0,0,1,1,2,2],"right_children":[2,4,6,-1,-1,-1,-1],"split_conditions":[1E0,7.7E-1,7.7E-1,1.0208932E-2,-1.1409456E-2,-7.1159587E-3,6.226219E-3],"split_indices":[10,0,0,0,0,0,0],"split_type":[0,0,0,0,0,0,0],"sum_hessian":[2.2898607E2,6.0933266E1,1.680528E2,9.959486E0,5.0973778E1,4.45491E1,1.235037E2],"tree_param":{"num_deleted":"0","num_feature":"128","num_nodes":"7","size_leaf_vector":"1"}}]},"name":"gbtree"},"learner_model_param":{"base_score":"[2.0387714E-9]","boost_from_average":"1","num_class":"0","num_feature":"128","num_target":"1"},"objective":{"lambdarank_param":{"lambdarank_bias_norm":"1","lambdarank_normalization":"1","lambdarank_num_pair_per_sample":"4294967295","lambdarank_pair_method":"topk","lambdarank_score_normalization":"1","lambdarank_unbiased":"0","ndcg_exp_gain":"1"},"name":"rank:pairwise"}},"version":[3,2,0]}